{
  "kind": "collectionType",
  "collectionName": "dentistas",
  "info": {
    "singularName": "dentista",
    "pluralName": "dentistas",
    "displayName": "Dentista"
  },
  "options": {
    "draftAndPublish": true
  },
  "pluginOptions": {},
  "attributes": {
    "Codigo_Minsa": {
      "type": "string",
      "required": true
    },
    "Especialidad": {
      "type": "string",
      "required": true
    },
    "nombre": {
      "type": "string",
      "maxLength": 50,
      "required": true
    },
    "apellido": {
      "type": "string",
      "maxLength": 50,
      "required": true
    },
    "telefono": {
      "type": "integer"
    },
    "estado": {
      "type": "boolean",
      "required": false,
      "default": true
    },
    "users_permissions_user": {
      "type": "relation",
      "relation": "oneToOne",
      "target": "plugin::users-permissions.user",
      "mappedBy": "dentista"
    }
  }
}
